LICENSE.txt
README.md
setup.py
Flask_Alcool.egg-info/PKG-INFO
Flask_Alcool.egg-info/SOURCES.txt
Flask_Alcool.egg-info/dependency_links.txt
Flask_Alcool.egg-info/not-zip-safe
Flask_Alcool.egg-info/requires.txt
Flask_Alcool.egg-info/top_level.txt
flask_alcool/__init__.py
flask_alcool/alcool.py
flask_alcool/url_if_auth.py