Metadata-Version: 1.1
Name: Flask-Alcool
Version: 0.4
Summary: Implement access control lists as decorators for flask.
Home-page: http://github.com/Kozea/flask-alcool
Author: Yohann Rebattu
Author-email: yohann.rebattu@kozea.fr
License: Beer License
Platform: UNKNOWN
Classifier: Development Status :: 3 - Alpha
Classifier: Environment :: Web Environment
Classifier: Intended Audience :: Developers
Classifier: Operating System :: OS Independent
Classifier: Programming Language :: Python
Classifier: Programming Language :: Python :: 3
Classifier: Topic :: Internet :: WWW/HTTP :: Dynamic Content
Classifier: Topic :: Software Development :: Libraries :: Python Modules
